[{"id":0,"info":{"pname":"이숙자","page":"90세","sex":"여","padr":"충남 천안시 서북구 검은들3길 5"},"list":{"memo":"안동현 관리사님에게 인수인계 잘 받았습니다.","todo":"구강관리,식사하기,신체기능유지"},"share":{"shareName":null,"shareID":null}},{"id":1,"info":{"pname":"양순이","page":"82세","sex":"여","padr":"충남 천안시 동남구 고재1길 5"},"list":{"memo":"","todo":"책읽기,환복,목욕하기"},"share":{"shareName":null,"shareID":null}},{"id":2,"info":{"pname":"정양봉","page":"70세","sex":"남","padr":"충남 천안시 서북구 성거읍 궝말1길 3-4"},"list":{"memo":null,"todo":null},"share":{"shareName":null,"shareID":null}},{"id":3,"info":{"pname":"구동룡","page":"65세","sex":"남","padr":"충남 천안시 서북구 나사렛대길 22-6"},"list":{"memo":"김성현 관리자 인수인계!! 인수인계 사항 확인 완료!!!","todo":"목욕하기,구강관리"},"share":{"shareName":null,"shareID":null}},{"id":4,"info":{"pname":"김춘배","page":"67세","sex":"남","padr":"충남 아산시 배방읍 천안천길 206"},"list":{"memo":null,"todo":null},"share":{"shareName":null,"shareID":null}}]